nabu/__init__.py
nabu/_version.py
nabu/build_flow.py
nabu/dalitz_utils.py
nabu/goodness_of_fit.py
nabu/likelihood.py
nabu/plotting.py
nabu/tensorboard.py
nabu/transform_base.py
nabu/flow/__init__.py
nabu/flow/_bijectors.py
nabu/flow/_flow_likelihood.py
nabu/flow/_flows.py
nabu/flow/_serialisation_utils.py
nabu/flow/_train.py
nabu/flow/metrics.py
nabu_hep-0.0.1.data/scripts/nabu-fit-to-data
nabu_hep-0.0.1.dist-info/LICENSE
nabu_hep-0.0.1.dist-info/METADATA
nabu_hep-0.0.1.dist-info/WHEEL
nabu_hep-0.0.1.dist-info/top_level.txt
nabu_hep-0.0.1.dist-info/RECORD
